{
	"class" : {
		 },
	"instance" : {
		"assertHierarchy:equals:" : "TB 6/27/2016 21:19",
		"sampleComplexMethod:b:" : "lcj 6/15/2016 12:58",
		"testAssignment" : "MiB 7/11/2019 09:32",
		"testAssignmentInBlock" : "MiB 7/11/2019 09:32",
		"testBlock" : "MiB 7/11/2019 09:32",
		"testBlockCommentBug" : "gw 7/9/2019 16:45",
		"testCascade" : "MiB 7/11/2019 09:32",
		"testCascadeAfterNew" : "MiB 7/11/2019 09:32",
		"testCascadeWithMessageSendArgument" : "MiB 7/11/2019 09:32",
		"testChainedMessage" : "MiB 7/11/2019 09:33",
		"testCharacters" : "MiB 7/11/2019 09:33",
		"testComments" : "MiB 7/11/2019 09:33",
		"testComplexMethod" : "MiB 7/11/2019 09:33",
		"testCurlyBracketArray" : "MiB 7/11/2019 09:33",
		"testIfTrueIfFalse" : "MiB 7/11/2019 09:33",
		"testMessagePrecedence" : "MiB 7/11/2019 09:33",
		"testMultipleTemporariesDeclaration" : "MiB 7/11/2019 09:33",
		"testNamedMessage" : "MiB 7/11/2019 09:34",
		"testNamedMessageMethod" : "MiB 7/11/2019 09:34",
		"testNestedBlocks" : "MiB 7/11/2019 09:34",
		"testNestedNamedMessage" : "MiB 7/11/2019 09:34",
		"testParseBinaryMessageDeclaration" : "MiB 7/11/2019 09:34",
		"testPragmaCollecting" : "MiB 7/11/2019 09:34",
		"testPragmaParsing" : "MiB 7/11/2019 09:36",
		"testPragmaPositioning" : "MiB 7/11/2019 09:34",
		"testReturnStatement" : "MiB 7/11/2019 09:35",
		"testSimpleAssignment" : "MiB 7/11/2019 09:35",
		"testSimpleMessagePrecedence" : "MiB 7/11/2019 09:35",
		"testSimpleMethod" : "MiB 7/11/2019 09:35",
		"testSymbols" : "MiB 7/11/2019 09:36",
		"testTemporaryDeclaration" : "MiB 7/11/2019 09:36",
		"testTokenizerParserInteraction" : "MiB 7/11/2019 09:37",
		"testUnaryMethodDeclaration" : "MiB 7/11/2019 09:37",
		"testWhitespacesInMethod" : "MiB 7/11/2019 09:37" } }
