{
	"class" : {
		"precedenceForBinary" : "kiwi 7/7/2019 15:28",
		"receiver:selector:" : "TB 6/27/2016 17:49",
		"receiver:selector:argument:" : "gw 6/2/2019 11:14",
		"receiver:selector:arguments:" : "TB 6/23/2016 12:06" },
	"instance" : {
		"accept:" : "lcj 7/29/2016 19:32",
		"addArgument:" : "kiwi 7/25/2019 11:59",
		"argumentDepth" : "MiB 5/25/2019 15:31",
		"argumentDepth:" : "MiB 5/25/2019 15:30",
		"arguments" : "TB 6/20/2016 12:17",
		"arguments:" : "gw 5/27/2019 10:36",
		"ifInCascade:" : "TB 6/28/2016 14:38",
		"ifNotInCascade:" : "TB 6/28/2016 14:42",
		"initialize" : "MiB 5/25/2019 15:36",
		"isBinaryMessage" : "kiwi 7/25/2019 11:59",
		"isInCascade" : "kiwi 7/25/2019 11:59",
		"isMessageNode" : "MiB 7/6/2019 12:40",
		"isNamedMessage" : "kiwi 7/25/2019 11:59",
		"isUnaryMessage" : "kiwi 7/25/2019 11:59",
		"matches:" : "TB 6/23/2016 11:37",
		"nodesDo:" : "TB 6/27/2016 21:29",
		"precedence" : "kiwi 7/7/2019 15:28",
		"receiver" : "lcj 6/1/2016 19:11",
		"receiver:" : "gw 5/27/2019 10:38",
		"receiverDepth" : "MiB 5/25/2019 15:18",
		"receiverDepth:" : "MiB 5/25/2019 15:18",
		"selector" : "lcj 6/1/2016 19:11",
		"selector:" : "gw 5/27/2019 10:38",
		"shallowMatch:" : "TB 6/27/2016 21:28" } }
